hecto/__init__.py
hecto/main.py
hecto/prompt.py
hecto/utils.py
hecto/vcs.py
hecto-2.2.1.dist-info/licenses/LICENSE
hecto-2.2.1.dist-info/METADATA
hecto-2.2.1.dist-info/WHEEL
hecto-2.2.1.dist-info/top_level.txt
hecto-2.2.1.dist-info/RECORD
