Metadata-Version: 2.4
Name: hecto
Version: 2.2.1
Summary: A small library for rendering blueprints of projects
Author-email: Juan Pablo Scaletti <juanpablo@jpscaletti.com>
License-Expression: MIT
Project-URL: repository, https://github.com/jpsca/hecto
Classifier: Development Status :: 5 - Production/Stable
Classifier: Environment :: Web Environment
Classifier: Intended Audience :: Developers
Classifier: Programming Language :: Python :: 3 :: Only
Classifier: Programming Language :: Python :: 3.10
Classifier: Programming Language :: Python :: 3.11
Classifier: Programming Language :: Python :: 3.12
Classifier: Programming Language :: Python :: 3.13
Classifier: Topic :: Software Development :: Libraries
Classifier: Topic :: Software Development :: Libraries :: Python Modules
Classifier: Typing :: Typed
Requires-Python: <4,>=3.10
License-File: LICENSE
Requires-Dist: jinja2>=2.4
Dynamic: license-file
